Workbook
Name Aporte: Planilha1!$D$14
Name Dividendo_Mensal: Planilha1!$D$18
Name Patrimonio_Acumulado: Planilha1!$D$17
Name Qtde_Anos: Planilha1!$D$15
Name Rendimento_carteira: Planilha1!$D$10
Name Salario: Planilha1!$D$9
Name Sugestao_investimento: Planilha1!$D$11
Name Taxa_Mensal: Planilha1!$D$16

Sheet Planilha1
B8: CONFIGURAÇÕES
B9: Salário | D9: 2000
B10: Rendimento Carteira | D10: 0.01
B11: Sugestão de Investimento (30%) | D11: =D9*30% -> 600
B13: INVESTIMENTO MENSAL
B14: Quanto Investir Por Mês? | D14: 500
B15: Por Quantos Anos? | D15: 3
B16: Taxa de Rendimento Mensal? | D16: 0.0108
B17: Patrimônio Acumulado? | D17: =FV(Taxa_Mensal,Qtde_Anos*12,Aporte*-1) -> 21858.221
B18: Dividendos Mensal? | D18: =D17*Rendimento_carteira -> 218.58221
B20: CENÁRIOS | D20: Dividendo
A21: 2 | B21: Quanto em 2 Anos? | C21: =FV($D$16,$A21*12,$D$14*-1) -> 13615.432 | D21: =C21*Rendimento_carteira -> 136.15432
A22: 5 | B22: Quanto em 5 Anos? | C22: =FV($D$16,$A22*12,$D$14*-1) -> 41902.01 | D22: =C22*Rendimento_carteira -> 419.0201
A23: 10 | B23: Quanto em 10 Anos? | C23: =FV($D$16,$A23*12,$D$14*-1) -> 121728.83 | D23: =C23*Rendimento_carteira -> 1217.2883
A24: 20 | B24: Quanto em 20 Anos? | C24: =FV($D$16,$A24*12,$D$14*-1) -> 563524.5 | D24: =C24*Rendimento_carteira -> 5635.245
A25: 30 | B25: Quanto em 30 Anos? | C25: =FV($D$16,$A25*12,$D$14*-1) -> 2166952.4 | D25: =C25*Rendimento_carteira -> 21669.524
B27: PERFIL | D27: CONSERVADOR
B28: VALOR A SER INVESTIDO POR MÊS | D28: =Aporte -> 500
B30: TIPO DE FII | C30: PERCENTUAL SUGERIDO | D30: VALORES
B31: PAPEL | C31: =VLOOKUP($D$27&"-"&B31,Planilha2!A:D,4,FALSE) -> 0.3 | D31: =C31*$D$28 -> 150
B32: TIJOLO | C32: =VLOOKUP($D$27&"-"&B32,Planilha2!A:D,4,FALSE) -> 0.5 | D32: =C32*$D$28 -> 250
B33: HÍBRIDOS | C33: =VLOOKUP($D$27&"-"&B33,Planilha2!A:D,4,FALSE) -> 0.1 | D33: =C33*$D$28 -> 50
B34: FOFs | C34: =VLOOKUP($D$27&"-"&B34,Planilha2!A:D,4,FALSE) -> 0.1 | D34: =C34*$D$28 -> 50
B35: DESENVOLVIMENTO | C35: =VLOOKUP($D$27&"-"&B35,Planilha2!A:D,4,FALSE) -> 0 | D35: =C35*$D$28 -> 0
B36: HOTELARIAS | C36: =VLOOKUP($D$27&"-"&B36,Planilha2!A:D,4,FALSE) -> 0 | D36: =C36*$D$28 -> 0
B37: =SUM(D31:D36) -> 500

Sheet Planilha2
A1: CHAVE COMPOSTA | B1: PERFIL | C1: TIPO DE FII | D1: %
A2: =B2&"-"&C2 -> CONSERVADOR-PAPEL | B2: CONSERVADOR | C2: PAPEL | D2: 0.3
A3: =B3&"-"&C3 -> CONSERVADOR-TIJOLO | B3: CONSERVADOR | C3: TIJOLO | D3: 0.5
A4: =B4&"-"&C4 -> CONSERVADOR-HÍBRIDOS | B4: CONSERVADOR | C4: HÍBRIDOS | D4: 0.1
A5: =B5&"-"&C5 -> CONSERVADOR-FOFs | B5: CONSERVADOR | C5: FOFs | D5: 0.1
A6: =B6&"-"&C6 -> CONSERVADOR-DESENVOLVIMENTO | B6: CONSERVADOR | C6: DESENVOLVIMENTO | D6: 0
A7: =B7&"-"&C7 -> CONSERVADOR-HOTELARIAS | B7: CONSERVADOR | C7: HOTELARIAS | D7: 0
A8: =B8&"-"&C8 -> MODERADO-PAPEL | B8: MODERADO | C8: PAPEL | D8: 0.32
A9: =B9&"-"&C9 -> MODERADO-TIJOLO | B9: MODERADO | C9: TIJOLO | D9: 0.4
A10: =B10&"-"&C10 -> MODERADO-HÍBRIDOS | B10: MODERADO | C10: HÍBRIDOS | D10: 0.08
A11: =B11&"-"&C11 -> MODERADO-FOFs | B11: MODERADO | C11: FOFs | D11: 0.1
A12: =B12&"-"&C12 -> MODERADO-DESENVOLVIMENTO | B12: MODERADO | C12: DESENVOLVIMENTO | D12: 0.05
A13: =B13&"-"&C13 -> MODERADO-HOTELARIAS | B13: MODERADO | C13: HOTELARIAS | D13: 0.05
... A19: =B19&"-"&C19 -> AGRESSIVO-HOTELARIAS | B19: AGRESSIVO | C19: HOTELARIAS | D19: 0.1
